neewerlite/__init__.py
neewerlite/client.py
neewerlite/exceptions.py
neewerlite/protocol.py
neewerlite/scanner.py
neewerlite-0.2.2.dist-info/METADATA
neewerlite-0.2.2.dist-info/WHEEL
neewerlite-0.2.2.dist-info/licenses/LICENSE
neewerlite-0.2.2.dist-info/RECORD
