Metadata-Version: 2.4
Name: neewerlite
Version: 0.2.2
Summary: A clean Python library for controlling Neewer RGB lights via Bluetooth LE.
Project-URL: Homepage, https://github.com/yourusername/neewerlite
Author-email: Mathieu Garnault <mathieu@example.com>
License-File: LICENSE
Requires-Python: >=3.9
Requires-Dist: bleak>=0.20.0
